jarowinkler/__init__.py
jarowinkler/__init__.pyi
jarowinkler/py.typed
jarowinkler-2.0.1.dist-info/LICENSE
jarowinkler-2.0.1.dist-info/METADATA
jarowinkler-2.0.1.dist-info/WHEEL
jarowinkler-2.0.1.dist-info/top_level.txt
jarowinkler-2.0.1.dist-info/RECORD
