Metadata-Version: 2.1
Name: jarowinkler
Version: 2.0.1
Summary: library for fast approximate string matching using Jaro and Jaro-Winkler similarity
Home-page: https://github.com/maxbachmann/JaroWinkler
Author: Max Bachmann
Author-email: pypi@maxbachmann.de
License: MIT
Keywords: string,comparison,edit-distance
Classifier: Programming Language :: Python :: 3
Classifier: Programming Language :: Python :: 3.8
Classifier: Programming Language :: Python :: 3.9
Classifier: Programming Language :: Python :: 3.10
Classifier: Programming Language :: Python :: 3.11
Classifier: Programming Language :: Python :: 3.12
Classifier: License :: OSI Approved :: MIT License
Requires-Python: >=3.8
License-File: LICENSE
Requires-Dist: rapidfuzz <4.0.0,>=3.5.2
